geneticnets/__init__.py
geneticnets/base.py
geneticnets-0.1.1.dist-info/METADATA
geneticnets-0.1.1.dist-info/WHEEL
geneticnets-0.1.1.dist-info/top_level.txt
geneticnets-0.1.1.dist-info/RECORD
