Metadata-Version: 2.1
Name: geneticnets
Version: 0.1.1
Requires-Dist: numpy
